es100/__init__.py
es100/es100.py
es100/gpio_control.py
es100/i2c_control.py
wwvb/__init__.py
wwvb/__main__.py
wwvb/config.py
wwvb/misc.py
wwvb/ntpdriver28.py
wwvb/sun.py
wwvb/wwvb.py
es100_wwvb-0.4.4.dist-info/LICENSE
es100_wwvb-0.4.4.dist-info/METADATA
es100_wwvb-0.4.4.dist-info/WHEEL
es100_wwvb-0.4.4.dist-info/entry_points.txt
es100_wwvb-0.4.4.dist-info/top_level.txt
es100_wwvb-0.4.4.dist-info/RECORD
