Metadata-Version: 2.1
Name: es100-wwvb
Version: 0.4.4
Summary: WWVB 60Khz Full functionality receiver/parser for i2c bus based ES100-MOD receiver
Home-page: https://github.com/mahtin/es100-wwvb
Download-URL: https://github.com/mahtin/es100-wwvb/archive/refs/tags/0.4.4.tar.gz
Author: Martin J Levy
Author-email: mahtin@mahtin.com
License: OSI Approved :: MIT License
Keywords: WWVB,ES100,NIST,Time,Time Synchronization,VLW,Very Long Wavelength,NTP
Classifier: Development Status :: 4 - Beta
Classifier: Intended Audience :: Developers
Classifier: Intended Audience :: System Administrators
Classifier: Topic :: Communications :: Ham Radio
Classifier: Topic :: System :: Networking :: Time Synchronization
Classifier: License :: OSI Approved :: MIT License
Classifier: Programming Language :: Python :: 3
Requires-Python: >=3.7
License-File: LICENSE
Requires-Dist: smbus
Requires-Dist: ephem
Requires-Dist: RPi.GPIO
Requires-Dist: sysv-ipc
